Maps/Level01.py
Maps/Level02.py
Maps/Level03.py
Maps/Level04.py
Maps/Level05.py
Maps/Level06.py
Maps/Level07.py
Maps/Level08.py
Maps/Level09.py
Maps/Level10.py
Maps/LevelBase.py
Maps/MapManager.py
Maps/__init__.py
Resources/__init__.py.py
Resources/collision/Collision.py
Resources/collision/__init__.py
Resources/sounds/Sounds.py
Resources/sounds/__init__.py
Resources/sounds/sound_0.mp3
Resources/sprites/__init__.py
Resources/sprites/sprite.py
Resources/sprites/Player/Player.py
Resources/sprites/Player/__init__.py
Resources/sprites/Player/knight_full_15fps_0.png
Resources/sprites/background/BackGround.py
Resources/sprites/background/__init__.py
Resources/sprites/background/bg_0.png
Resources/sprites/background/bg_1.png
Resources/sprites/background/bg_2.png
Resources/sprites/boulder/__init__.py
Resources/sprites/boulder/boulder.png
Resources/sprites/boulder/boulder.py
Resources/sprites/bridge/__init__.py
Resources/sprites/bridge/bridge.py
Resources/sprites/bridge/bridge_0.png
Resources/sprites/bridge/bridge_1.png
Resources/sprites/castle/Castle01.py
Resources/sprites/castle/__init__.py
Resources/sprites/castle/castle_0.png
Resources/sprites/equipage/__init__.py
Resources/sprites/equipage/equipage.py
Resources/sprites/equipage/knight_full_15fps_1.png
Resources/sprites/flovers/__init__.py
Resources/sprites/flovers/flovers.py
Resources/sprites/flovers/flovers_0.png
Resources/sprites/flovers/flovers_1.png
Resources/sprites/flovers/flovers_2.png
Resources/sprites/grass/Grass.py
Resources/sprites/grass/__init__.py
Resources/sprites/grass/grass_0.png
Resources/sprites/grass/grass_1.png
Resources/sprites/grass/grass_2.png
Resources/sprites/grass/grass_3.png
Resources/sprites/mill/__init__.py
Resources/sprites/mill/mill.py
Resources/sprites/mill/mill_0.png
Resources/sprites/mill/mill_1.png
Resources/sprites/pine/Pine.py
Resources/sprites/pine/__init__.py
Resources/sprites/pine/pine_0.png
Resources/sprites/pine/pine_1.png
Resources/sprites/pine/pine_2.png
mc_knight-0.0.11.dist-info/METADATA
mc_knight-0.0.11.dist-info/WHEEL
mc_knight-0.0.11.dist-info/top_level.txt
mc_knight-0.0.11.dist-info/RECORD
