Metadata-Version: 2.1
Name: mc-knight
Version: 0.0.11
Summary: UNKNOWN
Home-page: https://www.coding4fun.com.cn/
Author: 魔扣少儿编程_Hugn
Author-email: wang1183478375@outlook.com
License: UNKNOWN
Platform: UNKNOWN
Requires-Dist: pygame (>=1.9.4)
